{
  "title": "Bayesian rational-identification of (SG) closure asymptotes",
  "method": {
    "prior": "Occam: P(p/q) \u221d 1 / (q \u00b7 log(q+1))",
    "likelihood": "Gaussian N(p/q; asymptote, sigma=ci95_half/1.96)",
    "q_max": 50,
    "window": "10 * ci95_half around asymptote"
  },
  "results": [
    {
      "key": "lambda_inf_vac",
      "target": {
        "asymptote": 0.3732,
        "ci95_half": 0.003,
        "label": "Vacuum-branch lambda_inf (low-N regime)",
        "registered_rational": [
          3,
          8
        ]
      },
      "summary": {
        "n_candidates": 47,
        "top_rational": "3/8",
        "top_posterior": 0.7143212437106249,
        "second_rational": "16/43",
        "second_posterior": 0.11861683114611987,
        "posterior_odds_top_vs_second": 6.022090093021267
      },
      "table": [
        {
          "rational": "3/8",
          "p": 3,
          "q": 8,
          "value": 0.375,
          "prior": 0.08910251737406975,
          "likelihood": 130.53755071984577,
          "posterior": 0.7143212437106249,
          "z_score": 1.1760000000000155
        },
        {
          "rational": "16/43",
          "p": 16,
          "q": 43,
          "value": 0.37209302325581395,
          "prior": 0.009625273130743706,
          "likelihood": 200.66199390846705,
          "posterior": 0.11861683114611987,
          "z_score": -0.7232248062015382
        },
        {
          "rational": "13/35",
          "p": 13,
          "q": 35,
          "value": 0.37142857142857144,
          "prior": 0.012487533347713456,
          "likelihood": 133.41154955799382,
          "posterior": 0.10231474394130101,
          "z_score": -1.1573333333333093
        },
        {
          "rational": "10/27",
          "p": 10,
          "q": 27,
          "value": 0.37037037037037035,
          "prior": 0.017408405621364215,
          "likelihood": 47.196468115683395,
          "posterior": 0.050458766485849814,
          "z_score": -1.848691358024689
        },
        {
          "rational": "17/46",
          "p": 17,
          "q": 46,
          "value": 0.3695652173913043,
          "prior": 0.008843398558894227,
          "likelihood": 15.54113497437858,
          "posterior": 0.008440536708241176,
          "z_score": -2.3747246376811595
        },
        {
          "rational": "7/19",
          "p": 7,
          "q": 19,
          "value": 0.3684210526315789,
          "prior": 0.027516792584907437,
          "likelihood": 1.9916035000114918,
          "posterior": 0.0033656490107928996,
          "z_score": -3.1222456140350854
        },
        {
          "rational": "17/45",
          "p": 17,
          "q": 45,
          "value": 0.37777777777777777,
          "prior": 0.009090697464588378,
          "likelihood": 2.9762445929769274,
          "posterior": 0.001661628591514103,
          "z_score": 2.9908148148148235
        },
        {
          "rational": "14/37",
          "p": 14,
          "q": 37,
          "value": 0.3783783783783784,
          "prior": 0.011636956114403952,
          "likelihood": 0.8522319281165083,
          "posterior": 0.0006090673643713728,
          "z_score": 3.3832072072072363
        },
        {
          "rational": "11/29",
          "p": 11,
          "q": 29,
          "value": 0.3793103448275862,
          "prior": 0.015879052163532973,
          "likelihood": 0.09024291812873207,
          "posterior": 8.800469415991272e-05,
          "z_score": 3.992091954022991
        },
        {
          "rational": "18/49",
          "p": 18,
          "q": 49,
          "value": 0.3673469387755102,
          "prior": 0.008170656056258446,
          "likelihood": 0.17406280969443802,
          "posterior": 8.734359255158584e-05,
          "z_score": -3.8239999999999714
        },
        {
          "rational": "11/30",
          "p": 11,
          "q": 30,
          "value": 0.36666666666666664,
          "prior": 0.015203181562713395,
          "likelihood": 0.028820738698005565,
          "posterior": 2.6909629741377645e-05,
          "z_score": -4.268444444444445
        },
        {
          "rational": "19/50",
          "p": 19,
          "q": 50,
          "value": 0.38,
          "prior": 0.007966914481553167,
          "likelihood": 0.013494209314790109,
          "posterior": 6.602459258597749e-06,
          "z_score": 4.4426666666666845
        },
        {
          "rational": "15/41",
          "p": 15,
          "q": 41,
          "value": 0.36585365853658536,
          "prior": 0.010220441158943458,
          "likelihood": 0.002592900942456987,
          "posterior": 1.627510128669972e-06,
          "z_score": -4.79960975609755
        },
        {
          "rational": "8/21",
          "p": 8,
          "q": 21,
          "value": 0.38095238095238093,
          "prior": 0.024128490048998807,
          "likelihood": 0.0007007209684420635,
          "posterior": 1.0383490994085869e-06,
          "z_score": 5.06488888888889
        },
        {
          "rational": "13/34",
          "p": 13,
          "q": 34,
          "value": 0.38235294117647056,
          "prior": 0.012956669133926901,
          "likelihood": 4.476889534026318e-06,
          "posterior": 3.562360603549278e-09,
          "z_score": 5.979921568627449
        },
        {
          "rational": "4/11",
          "p": 4,
          "q": 11,
          "value": 0.36363636363636365,
          "prior": 0.05729960734772622,
          "likelihood": 8.679621183437837e-07,
          "posterior": 3.054362290412448e-09,
          "z_score": -6.2482424242424015
        },
        {
          "rational": "18/47",
          "p": 18,
          "q": 47,
          "value": 0.3829787234042553,
          "prior": 0.008608169876499488,
          "likelihood": 3.5718345801531046e-07,
          "posterior": 1.8882969803651106e-10,
          "z_score": 6.388765957446822
        },
        {
          "rational": "5/13",
          "p": 5,
          "q": 13,
          "value": 0.38461538461538464,
          "prior": 0.04565225477815143,
          "likelihood": 2.1765376873562534e-10,
          "posterior": 6.102342174537182e-13,
          "z_score": 7.4580512820513105
        },
        {
          "rational": "17/47",
          "p": 17,
          "q": 47,
          "value": 0.3617021276595745,
          "prior": 0.008608169876499488,
          "likelihood": 1.4540518975849293e-10,
          "posterior": 7.687035180072894e-14,
          "z_score": -7.511943262411316
        },
        {
          "rational": "13/36",
          "p": 13,
          "q": 36,
          "value": 0.3611111111111111,
          "prior": 0.01204853636869105,
          "likelihood": 7.421513458288122e-12,
          "posterior": 5.4915495234855574e-15,
          "z_score": -7.898074074074062
        },
        {
          "rational": "9/25",
          "p": 9,
          "q": 25,
          "value": 0.36,
          "prior": 0.01922872340137322,
          "likelihood": 1.845319129158388e-14,
          "posterior": 2.1791647657616065e-17,
          "z_score": -8.623999999999992
        },
        {
          "rational": "17/44",
          "p": 17,
          "q": 44,
          "value": 0.38636363636363635,
          "prior": 0.00935098499743782,
          "likelihood": 2.2642766642498836e-14,
          "posterior": 1.3003341943449332e-17,
          "z_score": 8.600242424242433
        },
        {
          "rational": "12/31",
          "p": 12,
          "q": 31,
          "value": 0.3870967741935484,
          "prior": 0.014577976645961898,
          "likelihood": 3.2816285095226104e-16,
          "posterior": 2.938020341966145e-19,
          "z_score": 9.079225806451621
        },
        {
          "rational": "14/39",
          "p": 14,
          "q": 39,
          "value": 0.358974358974359,
          "prior": 0.010886677023414474,
          "likelihood": 4.558908125188136e-17,
          "posterior": 3.0480656105215245e-20,
          "z_score": -9.294085470085452
        },
        {
          "rational": "19/49",
          "p": 19,
          "q": 49,
          "value": 0.3877551020408163,
          "prior": 0.008170656056258446,
          "likelihood": 6.0253187468709535e-18,
          "posterior": 3.0234659922127224e-21,
          "z_score": 9.50933333333334
        },
        {
          "rational": "7/18",
          "p": 7,
          "q": 18,
          "value": 0.3888888888888889,
          "prior": 0.029551487466837143,
          "likelihood": 3.996530545925237e-21,
          "posterior": 7.253216064632135e-24,
          "z_score": 10.250074074074092
        },
        {
          "rational": "5/14",
          "p": 5,
          "q": 14,
          "value": 0.35714285714285715,
          "prior": 0.04131137619598029,
          "likelihood": 3.29688281541322e-22,
          "posterior": 8.36452542923176e-25,
          "z_score": -10.490666666666645
        },
        {
          "rational": "16/41",
          "p": 16,
          "q": 41,
          "value": 0.3902439024390244,
          "prior": 0.010220441158943458,
          "likelihood": 3.094947584703239e-25,
          "posterior": 1.942634390434584e-28,
          "z_score": 11.135349593495958
        },
        {
          "rational": "16/45",
          "p": 16,
          "q": 45,
          "value": 0.35555555555555557,
          "prior": 0.009090697464588378,
          "likelihood": 3.629047078481681e-27,
          "posterior": 2.0260862967328816e-30,
          "z_score": -11.527703703703677
        },
        {
          "rational": "9/23",
          "p": 9,
          "q": 23,
          "value": 0.391304347826087,
          "prior": 0.02142719511378764,
          "likelihood": 1.0861968597623459e-28,
          "posterior": 1.4293612341508687e-31,
          "z_score": 11.828173913043504
        },
        {
          "rational": "11/31",
          "p": 11,
          "q": 31,
          "value": 0.3548387096774194,
          "prior": 0.014577976645961898,
          "likelihood": 1.4704855748382667e-29,
          "posterior": 1.3165160282176786e-32,
          "z_score": -11.99604301075266
        },
        {
          "rational": "17/48",
          "p": 17,
          "q": 48,
          "value": 0.3541666666666667,
          "prior": 0.008384176130120852,
          "likelihood": 6.888667935545741e-32,
          "posterior": 3.5470211306343096e-35,
          "z_score": -12.435111111111082
        },
        {
          "rational": "11/28",
          "p": 11,
          "q": 28,
          "value": 0.39285714285714285,
          "prior": 0.016611739250688713,
          "likelihood": 3.9908272354530254e-34,
          "posterior": 4.071422432164585e-37,
          "z_score": 12.842666666666675
        },
        {
          "rational": "6/17",
          "p": 6,
          "q": 17,
          "value": 0.35294117647058826,
          "prior": 0.0318751166612538,
          "likelihood": 2.3713955070443644e-36,
          "posterior": 4.6422006478729544e-39,
          "z_score": -13.235764705882321
        },
        {
          "rational": "13/33",
          "p": 13,
          "q": 33,
          "value": 0.3939393939393939,
          "prior": 0.013459029910552941,
          "likelihood": 3.5384579167426076e-38,
          "posterior": 2.924798325107396e-41,
          "z_score": 13.549737373737377
        },
        {
          "rational": "15/38",
          "p": 15,
          "q": 38,
          "value": 0.39473684210526316,
          "prior": 0.011250383038918463,
          "likelihood": 2.65466933642476e-41,
          "posterior": 1.834196560113267e-44,
          "z_score": 14.070736842105282
        },
        {
          "rational": "13/37",
          "p": 13,
          "q": 37,
          "value": 0.35135135135135137,
          "prior": 0.011636956114403952,
          "likelihood": 1.479575178354873e-42,
          "posterior": 1.0574128057623173e-45,
          "z_score": -14.274450450450422
        },
        {
          "rational": "17/43",
          "p": 17,
          "q": 43,
          "value": 0.3953488372093023,
          "prior": 0.009625273130743706,
          "likelihood": 8.829887177916434e-44,
          "posterior": 5.21958949984304e-47,
          "z_score": 14.470573643410855
        },
        {
          "rational": "19/48",
          "p": 19,
          "q": 48,
          "value": 0.3958333333333333,
          "prior": 0.008384176130120852,
          "likelihood": 8.60837616478285e-46,
          "posterior": 4.4325103841014946e-49,
          "z_score": 14.787111111111113
        },
        {
          "rational": "7/20",
          "p": 7,
          "q": 20,
          "value": 0.35,
          "prior": 0.025722029655755017,
          "likelihood": 3.3698104792686536e-48,
          "posterior": 5.3232742762166524e-51,
          "z_score": -15.15733333333333
        },
        {
          "rational": "15/43",
          "p": 15,
          "q": 43,
          "value": 0.3488372093023256,
          "prior": 0.009625273130743706,
          "likelihood": 2.5202149511862874e-53,
          "posterior": 1.4897684683286537e-56,
          "z_score": -15.91702325581393
        },
        {
          "rational": "8/23",
          "p": 8,
          "q": 23,
          "value": 0.34782608695652173,
          "prior": 0.02142719511378764,
          "likelihood": 5.4974757680354584e-58,
          "posterior": 7.234304424552396e-61,
          "z_score": -16.577623188405788
        },
        {
          "rational": "17/49",
          "p": 17,
          "q": 49,
          "value": 0.3469387755102041,
          "prior": 0.008170656056258446,
          "likelihood": 3.1154734791859894e-62,
          "posterior": 1.563324449656909e-65,
          "z_score": -17.15733333333332
        },
        {
          "rational": "2/5",
          "p": 2,
          "q": 5,
          "value": 0.4,
          "prior": 0.17482546686798836,
          "likelihood": 6.978284312614497e-65,
          "posterior": 7.492409202534122e-67,
          "z_score": 17.509333333333363
        },
        {
          "rational": "9/26",
          "p": 9,
          "q": 26,
          "value": 0.34615384615384615,
          "prior": 0.018277439461347644,
          "likelihood": 4.1230640754696925e-66,
          "posterior": 4.628108910950147e-69,
          "z_score": -17.670153846153834
        },
        {
          "rational": "10/29",
          "p": 10,
          "q": 29,
          "value": 0.3448275862068966,
          "prior": 0.015879052163532973,
          "likelihood": 6.34889824652113e-73,
          "posterior": 6.19143152751845e-76,
          "z_score": -18.53664367816089
        },
        {
          "rational": "11/32",
          "p": 11,
          "q": 32,
          "value": 0.34375,
          "prior": 0.013998127963058207,
          "likelihood": 1.0651965061935707e-78,
          "posterior": 9.157308066349204e-82,
          "z_score": -19.240666666666648
        }
      ]
    },
    {
      "key": "lambda_inf_mat",
      "target": {
        "asymptote": 0.3957,
        "ci95_half": 0.004,
        "label": "Matter-branch lambda_inf (high-N regime)",
        "registered_rational": [
          79,
          200
        ]
      },
      "summary": {
        "n_candidates": 62,
        "top_rational": "2/5",
        "top_posterior": 0.29222095627782796,
        "second_rational": "15/38",
        "second_posterior": 0.15485382203921008,
        "posterior_odds_top_vs_second": 1.887076162730007
      },
      "table": [
        {
          "rational": "2/5",
          "p": 2,
          "q": 5,
          "value": 0.4,
          "prior": 0.1327198707111458,
          "likelihood": 21.236945090529257,
          "posterior": 0.29222095627782796,
          "z_score": 2.1070000000000126
        },
        {
          "rational": "15/38",
          "p": 15,
          "q": 38,
          "value": 0.39473684210526316,
          "prior": 0.008540800199913729,
          "likelihood": 174.8799430227054,
          "posterior": 0.15485382203921008,
          "z_score": -0.47194736842104784
        },
        {
          "rational": "17/43",
          "p": 17,
          "q": 43,
          "value": 0.3953488372093023,
          "prior": 0.007307087624919033,
          "likelihood": 192.6091210012544,
          "posterior": 0.14591654171579002,
          "z_score": -0.17206976744186805
        },
        {
          "rational": "13/33",
          "p": 13,
          "q": 33,
          "value": 0.3939393939393939,
          "prior": 0.010217508590867145,
          "likelihood": 134.73957309117623,
          "posterior": 0.14273272000502507,
          "z_score": -0.862696969696976
        },
        {
          "rational": "19/48",
          "p": 19,
          "q": 48,
          "value": 0.3958333333333333,
          "prior": 0.006364900903421325,
          "likelihood": 195.06496085512256,
          "posterior": 0.12872244338126468,
          "z_score": 0.06533333333332614
        },
        {
          "rational": "11/28",
          "p": 11,
          "q": 28,
          "value": 0.39285714285714285,
          "prior": 0.012610908039521833,
          "likelihood": 74.08716888785068,
          "posterior": 0.09686630228957507,
          "z_score": -1.3930000000000018
        },
        {
          "rational": "9/23",
          "p": 9,
          "q": 23,
          "value": 0.391304347826087,
          "prior": 0.016266592139872676,
          "likelihood": 19.218816130071183,
          "posterior": 0.03241205542440066,
          "z_score": -2.153869565217381
        },
        {
          "rational": "16/41",
          "p": 16,
          "q": 41,
          "value": 0.3902439024390244,
          "prior": 0.007758913238024502,
          "likelihood": 5.483251895147521,
          "posterior": 0.004410851700992658,
          "z_score": -2.67348780487804
        },
        {
          "rational": "7/18",
          "p": 7,
          "q": 18,
          "value": 0.3888888888888889,
          "prior": 0.02243420061267302,
          "likelihood": 0.7454249265632911,
          "posterior": 0.00173379550975286,
          "z_score": -3.337444444444439
        },
        {
          "rational": "19/49",
          "p": 19,
          "q": 49,
          "value": 0.3877551020408163,
          "prior": 0.006202805774462504,
          "likelihood": 0.1000327504511925,
          "posterior": 6.433003032993129e-05,
          "z_score": -3.8930000000000042
        },
        {
          "rational": "12/31",
          "p": 12,
          "q": 31,
          "value": 0.3870967741935484,
          "prior": 0.011066964157705549,
          "likelihood": 0.027049324939437184,
          "posterior": 3.103618257283259e-05,
          "z_score": -4.215580645161293
        },
        {
          "rational": "19/47",
          "p": 19,
          "q": 47,
          "value": 0.40425531914893614,
          "prior": 0.0065349471878217895,
          "likelihood": 0.029854756496977827,
          "posterior": 2.0227349523094036e-05,
          "z_score": 4.192106382978712
        },
        {
          "rational": "17/42",
          "p": 17,
          "q": 42,
          "value": 0.40476190476190477,
          "prior": 0.00752679229104588,
          "likelihood": 0.010226087787199493,
          "posterior": 7.979998534990495e-06,
          "z_score": 4.440333333333338
        },
        {
          "rational": "17/44",
          "p": 17,
          "q": 44,
          "value": 0.38636363636363635,
          "prior": 0.007098860035185513,
          "likelihood": 0.005577504412978128,
          "posterior": 4.10498807263333e-06,
          "z_score": -4.574818181818184
        },
        {
          "rational": "15/37",
          "p": 15,
          "q": 37,
          "value": 0.40540540540540543,
          "prior": 0.008834269621262884,
          "likelihood": 0.0023991754172810915,
          "posterior": 2.1974348917597855e-06,
          "z_score": 4.755648648648661
        },
        {
          "rational": "13/32",
          "p": 13,
          "q": 32,
          "value": 0.40625,
          "prior": 0.010626768323507564,
          "likelihood": 0.0003076960025525775,
          "posterior": 3.390052548651364e-07,
          "z_score": 5.169500000000001
        },
        {
          "rational": "5/13",
          "p": 5,
          "q": 13,
          "value": 0.38461538461538464,
          "prior": 0.0346572010381285,
          "likelihood": 7.675282502788797e-05,
          "posterior": 2.7578536668475343e-07,
          "z_score": -5.431461538461526
        },
        {
          "rational": "11/27",
          "p": 11,
          "q": 27,
          "value": 0.4074074074074074,
          "prior": 0.013215702407357326,
          "likelihood": 1.3964489765855573e-05,
          "posterior": 1.913368792357905e-08,
          "z_score": 5.73662962962962
        },
        {
          "rational": "20/49",
          "p": 20,
          "q": 49,
          "value": 0.40816326530612246,
          "prior": 0.006202805774462504,
          "likelihood": 1.5577662683256388e-06,
          "posterior": 1.001783424291895e-09,
          "z_score": 6.1070000000000055
        },
        {
          "rational": "18/47",
          "p": 18,
          "q": 47,
          "value": 0.3829787234042553,
          "prior": 0.0065349471878217895,
          "likelihood": 7.140377012967503e-07,
          "posterior": 4.8377852816378e-10,
          "z_score": -6.233425531914892
        },
        {
          "rational": "9/22",
          "p": 9,
          "q": 22,
          "value": 0.4090909090909091,
          "prior": 0.017236813309229795,
          "likelihood": 8.751352202156953e-08,
          "posterior": 1.5639234942175682e-10,
          "z_score": 6.561545454545469
        },
        {
          "rational": "13/34",
          "p": 13,
          "q": 34,
          "value": 0.38235294117647056,
          "prior": 0.00983613819604644,
          "likelihood": 1.007405084276396e-07,
          "posterior": 1.0273350935258415e-10,
          "z_score": -6.540058823529422
        },
        {
          "rational": "8/21",
          "p": 8,
          "q": 21,
          "value": 0.38095238095238093,
          "prior": 0.018317297457448728,
          "likelihood": 8.947472280331265e-10,
          "posterior": 1.6992024405412493e-12,
          "z_score": -7.226333333333341
        },
        {
          "rational": "16/39",
          "p": 16,
          "q": 39,
          "value": 0.41025641025641024,
          "prior": 0.008264690453322832,
          "likelihood": 1.753210527919076e-09,
          "posterior": 1.5022562707152937e-12,
          "z_score": 7.1326410256410195
        },
        {
          "rational": "19/50",
          "p": 19,
          "q": 50,
          "value": 0.38,
          "prior": 0.006048134055645998,
          "likelihood": 2.7532399472738204e-11,
          "posterior": 1.7264294445083616e-14,
          "z_score": -7.692999999999995
        },
        {
          "rational": "7/17",
          "p": 7,
          "q": 17,
          "value": 0.4117647058823529,
          "prior": 0.024198198568969,
          "likelihood": 6.852484071374477e-12,
          "posterior": 1.7191526238150405e-14,
          "z_score": 7.8717058823529324
        },
        {
          "rational": "11/29",
          "p": 11,
          "q": 29,
          "value": 0.3793103448275862,
          "prior": 0.01205468395374568,
          "likelihood": 1.9320108148427064e-12,
          "posterior": 2.414619732020516e-15,
          "z_score": -8.030931034482766
        },
        {
          "rational": "14/37",
          "p": 14,
          "q": 37,
          "value": 0.3783783783783784,
          "prior": 0.008834269621262884,
          "likelihood": 4.4460993388838645e-14,
          "posterior": 4.072238215313811e-17,
          "z_score": -8.487594594594581
        },
        {
          "rational": "19/46",
          "p": 19,
          "q": 46,
          "value": 0.41304347826086957,
          "prior": 0.006713522545716054,
          "likelihood": 4.059540401791739e-14,
          "posterior": 2.825600008767018e-17,
          "z_score": 8.498304347826089
        },
        {
          "rational": "17/45",
          "p": 17,
          "q": 45,
          "value": 0.37777777777777777,
          "prior": 0.006901261090784659,
          "likelihood": 3.5024300389147e-15,
          "posterior": 2.5060012923154756e-18,
          "z_score": -8.781888888888892
        },
        {
          "rational": "12/29",
          "p": 12,
          "q": 29,
          "value": 0.41379310344827586,
          "prior": 0.01205468395374568,
          "likelihood": 1.6730162689753569e-15,
          "posterior": 2.0909293385027608e-18,
          "z_score": 8.86562068965517
        },
        {
          "rational": "17/41",
          "p": 17,
          "q": 41,
          "value": 0.4146341463414634,
          "prior": 0.007758913238024502,
          "likelihood": 3.979915636930521e-17,
          "posterior": 3.201534051809227e-20,
          "z_score": 9.277731707317065
        },
        {
          "rational": "3/8",
          "p": 3,
          "q": 8,
          "value": 0.375,
          "prior": 0.06764274563530147,
          "likelihood": 8.931008395798043e-21,
          "posterior": 6.263327033557369e-23,
          "z_score": -10.142999999999997
        },
        {
          "rational": "5/12",
          "p": 5,
          "q": 12,
          "value": 0.4166666666666667,
          "prior": 0.03863008126743373,
          "likelihood": 2.352880734489864e-21,
          "posterior": 9.423427617330414e-24,
          "z_score": 10.273666666666676
        },
        {
          "rational": "18/43",
          "p": 18,
          "q": 43,
          "value": 0.4186046511627907,
          "prior": 0.007307087624919033,
          "likelihood": 8.685741184442669e-26,
          "posterior": 6.580131352471257e-29,
          "z_score": 11.223279069767454
        },
        {
          "rational": "13/31",
          "p": 13,
          "q": 31,
          "value": 0.41935483870967744,
          "prior": 0.011066964157705549,
          "likelihood": 1.3114317421265225e-27,
          "posterior": 1.5047264607001144e-30,
          "z_score": 11.590870967741944
        },
        {
          "rational": "16/43",
          "p": 16,
          "q": 43,
          "value": 0.37209302325581395,
          "prior": 0.007307087624919033,
          "likelihood": 1.7206081107884724e-27,
          "posterior": 1.3034958254794053e-30,
          "z_score": -11.567418604651163
        },
        {
          "rational": "13/35",
          "p": 13,
          "q": 35,
          "value": 0.37142857142857144,
          "prior": 0.009479990765081844,
          "likelihood": 3.776169192923702e-29,
          "posterior": 3.711442380648846e-32,
          "z_score": -11.89299999999999
        },
        {
          "rational": "21/50",
          "p": 21,
          "q": 50,
          "value": 0.42,
          "prior": 0.006048134055645998,
          "likelihood": 3.1966713162222793e-29,
          "posterior": 2.0044847490339618e-32,
          "z_score": 11.906999999999993
        },
        {
          "rational": "8/19",
          "p": 8,
          "q": 19,
          "value": 0.42105263157894735,
          "prior": 0.020889548986658756,
          "likelihood": 6.02152578563317e-32,
          "posterior": 1.304124270541075e-34,
          "z_score": 12.4227894736842
        },
        {
          "rational": "10/27",
          "p": 10,
          "q": 27,
          "value": 0.37037037037037035,
          "prior": 0.013215702407357326,
          "likelihood": 6.926079095129835e-32,
          "posterior": 9.489887433214051e-35,
          "z_score": -12.411518518518525
        },
        {
          "rational": "17/46",
          "p": 17,
          "q": 46,
          "value": 0.3695652173913043,
          "prior": 0.006713522545716054,
          "likelihood": 4.787389322115505e-34,
          "posterior": 3.3322115243809984e-37,
          "z_score": -12.806043478260879
        },
        {
          "rational": "19/45",
          "p": 19,
          "q": 45,
          "value": 0.4222222222222222,
          "prior": 0.006901261090784659,
          "likelihood": 4.1345607955352466e-35,
          "posterior": 2.9582931226740117e-38,
          "z_score": 12.995888888888889
        },
        {
          "rational": "7/19",
          "p": 7,
          "q": 19,
          "value": 0.3684210526315789,
          "prior": 0.020889548986658756,
          "likelihood": 3.1173768865598872e-37,
          "posterior": 6.751522791592654e-40,
          "z_score": -13.366684210526323
        },
        {
          "rational": "11/26",
          "p": 11,
          "q": 26,
          "value": 0.4230769230769231,
          "prior": 0.013875435002113122,
          "likelihood": 1.6390723534301237e-37,
          "posterior": 2.357914732117664e-40,
          "z_score": 13.414692307692306
        },
        {
          "rational": "18/49",
          "p": 18,
          "q": 49,
          "value": 0.3673469387755102,
          "prior": 0.006202805774462504,
          "likelihood": 2.389648006930244e-40,
          "posterior": 1.5367579924605572e-43,
          "z_score": -13.892999999999988
        },
        {
          "rational": "14/33",
          "p": 14,
          "q": 33,
          "value": 0.42424242424242425,
          "prior": 0.010217508590867145,
          "likelihood": 6.555631002969414e-41,
          "posterior": 6.944530273744589e-44,
          "z_score": 13.985787878787885
        },
        {
          "rational": "11/30",
          "p": 11,
          "q": 30,
          "value": 0.36666666666666664,
          "prior": 0.011541592466760132,
          "likelihood": 2.202869234404805e-42,
          "posterior": 2.6359539348865043e-45,
          "z_score": -14.226333333333343
        },
        {
          "rational": "17/40",
          "p": 17,
          "q": 40,
          "value": 0.425,
          "prior": 0.008004492737381472,
          "likelihood": 3.403830300985707e-43,
          "posterior": 2.8247829193152137e-46,
          "z_score": 14.356999999999996
        },
        {
          "rational": "15/41",
          "p": 15,
          "q": 41,
          "value": 0.36585365853658536,
          "prior": 0.007758913238024502,
          "likelihood": 7.034059462546437e-45,
          "posterior": 5.658356343744396e-48,
          "z_score": -14.624707317073172
        },
        {
          "rational": "20/47",
          "p": 20,
          "q": 47,
          "value": 0.425531914893617,
          "prior": 0.0065349471878217895,
          "likelihood": 7.799981320772565e-45,
          "posterior": 5.28468381461569e-48,
          "z_score": 14.617638297872343
        },
        {
          "rational": "4/11",
          "p": 4,
          "q": 11,
          "value": 0.36363636363636365,
          "prior": 0.043499363194791675,
          "likelihood": 4.900193193611625e-52,
          "posterior": 2.209934823494156e-54,
          "z_score": -15.71118181818181
        },
        {
          "rational": "3/7",
          "p": 3,
          "q": 7,
          "value": 0.42857142857142855,
          "prior": 0.08168473544973143,
          "likelihood": 9.024313840477968e-55,
          "posterior": 7.642553028953704e-57,
          "z_score": 16.10699999999999
        },
        {
          "rational": "17/47",
          "p": 17,
          "q": 47,
          "value": 0.3617021276595745,
          "prior": 0.0065349471878217895,
          "likelihood": 1.067127697608108e-58,
          "posterior": 7.230058944704121e-62,
          "z_score": -16.658957446808497
        },
        {
          "rational": "13/36",
          "p": 13,
          "q": 36,
          "value": 0.3611111111111111,
          "prior": 0.009146723402252878,
          "likelihood": 8.21851734101887e-61,
          "posterior": 7.79367668701303e-64,
          "z_score": -16.948555555555554
        },
        {
          "rational": "9/25",
          "p": 9,
          "q": 25,
          "value": 0.36,
          "prior": 0.014597608286083925,
          "likelihood": 6.965527934140418e-65,
          "posterior": 1.054190522169095e-67,
          "z_score": -17.493000000000002
        },
        {
          "rational": "19/44",
          "p": 19,
          "q": 44,
          "value": 0.4318181818181818,
          "prior": 0.007098860035185513,
          "likelihood": 1.892861869495286e-66,
          "posterior": 1.3931276108613e-69,
          "z_score": 17.697909090909093
        },
        {
          "rational": "16/37",
          "p": 16,
          "q": 37,
          "value": 0.43243243243243246,
          "prior": 0.008834269621262884,
          "likelihood": 8.791484710545381e-69,
          "posterior": 8.052231243357095e-72,
          "z_score": 17.998891891891905
        },
        {
          "rational": "14/39",
          "p": 14,
          "q": 39,
          "value": 0.358974358974359,
          "prior": 0.008264690453322832,
          "likelihood": 9.334102135190827e-69,
          "posterior": 7.998020340849026e-72,
          "z_score": -17.9955641025641
        },
        {
          "rational": "13/30",
          "p": 13,
          "q": 30,
          "value": 0.43333333333333335,
          "prior": 0.011541592466760132,
          "likelihood": 2.82539119537083e-72,
          "posterior": 3.3808638854787477e-75,
          "z_score": 18.440333333333342
        },
        {
          "rational": "5/14",
          "p": 5,
          "q": 14,
          "value": 0.35714285714285715,
          "prior": 0.031361795314238355,
          "likelihood": 6.044866657117809e-76,
          "posterior": 1.965490752385526e-78,
          "z_score": -18.892999999999994
        },
        {
          "rational": "10/23",
          "p": 10,
          "q": 23,
          "value": 0.43478260869565216,
          "prior": 0.016266592139872676,
          "likelihood": 4.511796004552931e-78,
          "posterior": 7.609031751666873e-81,
          "z_score": 19.15047826086956
        }
      ]
    },
    {
      "key": "lambda_inf_pooled",
      "target": {
        "asymptote": 0.4082217913890619,
        "ci95_half": 0.003,
        "label": "Pooled-ladder weighted lambda_2 (branch-mixed; expect 2/5)",
        "registered_rational": [
          2,
          5
        ]
      },
      "summary": {
        "n_candidates": 48,
        "top_rational": "9/22",
        "top_posterior": 0.32927341467379856,
        "second_rational": "11/27",
        "second_posterior": 0.25747236406521323,
        "posterior_odds_top_vs_second": 1.2788689608271875
      },
      "table": [
        {
          "rational": "9/22",
          "p": 9,
          "q": 22,
          "value": 0.4090909090909091,
          "prior": 0.02257795109114813,
          "likelihood": 221.83572483880076,
          "posterior": 0.32927341467379856,
          "z_score": 0.5678235652068515
        },
        {
          "rational": "11/27",
          "p": 11,
          "q": 27,
          "value": 0.4074074074074074,
          "prior": 0.017310826382780798,
          "likelihood": 226.24144578358772,
          "posterior": 0.25747236406521323,
          "z_score": -0.5320642013476129
        },
        {
          "rational": "20/49",
          "p": 20,
          "q": 49,
          "value": 0.40816326530612246,
          "prior": 0.008124857123602705,
          "likelihood": 260.451820685723,
          "posterior": 0.13911814649442233,
          "z_score": -0.03823704085376504
        },
        {
          "rational": "13/32",
          "p": 13,
          "q": 32,
          "value": 0.40625,
          "prior": 0.01391966433474338,
          "likelihood": 113.67819362199698,
          "posterior": 0.10402712092584751,
          "z_score": -1.2882370408537709
        },
        {
          "rational": "16/39",
          "p": 16,
          "q": 39,
          "value": 0.41025641025641024,
          "prior": 0.010825653993634846,
          "likelihood": 107.73241564433611,
          "posterior": 0.0766727769078593,
          "z_score": 1.3292843266675871
        },
        {
          "rational": "7/17",
          "p": 7,
          "q": 17,
          "value": 0.4117647058823529,
          "prior": 0.03169644724825795,
          "likelihood": 17.889631740115078,
          "posterior": 0.037278003043530024,
          "z_score": 2.3147041356168043
        },
        {
          "rational": "15/37",
          "p": 15,
          "q": 37,
          "value": 0.40540540540540543,
          "prior": 0.011571727549435393,
          "likelihood": 47.95568997820742,
          "posterior": 0.03648203001167596,
          "z_score": -1.8400388426555578
        },
        {
          "rational": "17/42",
          "p": 17,
          "q": 42,
          "value": 0.40476190476190477,
          "prior": 0.009859104764421108,
          "likelihood": 20.25316120664143,
          "posterior": 0.013127165286172054,
          "z_score": -2.2604592630759894
        },
        {
          "rational": "19/47",
          "p": 19,
          "q": 47,
          "value": 0.40425531914893614,
          "prior": 0.008559918550076194,
          "likelihood": 9.073862398393917,
          "posterior": 0.005106254702635195,
          "z_score": -2.5914285302154907
        },
        {
          "rational": "19/46",
          "p": 19,
          "q": 46,
          "value": 0.41304347826086957,
          "prior": 0.008793828706454234,
          "likelihood": 1.8246119493500348,
          "posterior": 0.0010548462639681816,
          "z_score": 3.1501687562476794
        },
        {
          "rational": "12/29",
          "p": 12,
          "q": 29,
          "value": 0.41379310344827586,
          "prior": 0.015790045401325965,
          "likelihood": 0.34598011005596635,
          "posterior": 0.0003591494153006097,
          "z_score": 3.6399238786864547
        },
        {
          "rational": "17/41",
          "p": 17,
          "q": 41,
          "value": 0.4146341463414634,
          "prior": 0.010163152577325599,
          "likelihood": 0.04025950380724929,
          "posterior": 2.6899085544414117e-05,
          "z_score": 4.189405235568979
        },
        {
          "rational": "2/5",
          "p": 2,
          "q": 5,
          "value": 0.4,
          "prior": 0.17384551865716355,
          "likelihood": 0.00014142582092707668,
          "posterior": 1.6163405218632577e-06,
          "z_score": -5.3715703741870895
        },
        {
          "rational": "5/12",
          "p": 5,
          "q": 12,
          "value": 0.4166666666666667,
          "prior": 0.05060030934118002,
          "likelihood": 6.395998746478044e-05,
          "posterior": 2.1276598305507067e-07,
          "z_score": 5.517318514701796
        },
        {
          "rational": "18/43",
          "p": 18,
          "q": 43,
          "value": 0.4186046511627907,
          "prior": 0.009571320641142777,
          "likelihood": 2.6541063474752143e-08,
          "posterior": 1.6700552481854672e-11,
          "z_score": 6.7834683855028315
        },
        {
          "rational": "13/31",
          "p": 13,
          "q": 31,
          "value": 0.41935483870967744,
          "prior": 0.014496262795070576,
          "likelihood": 8.46921185221553e-10,
          "posterior": 8.071229616345444e-13,
          "z_score": 7.273590916135486
        },
        {
          "rational": "21/50",
          "p": 21,
          "q": 50,
          "value": 0.42,
          "prior": 0.00792225758040565,
          "likelihood": 3.612252279794405e-11,
          "posterior": 1.8813417143988185e-14,
          "z_score": 7.695096292479551
        },
        {
          "rational": "19/48",
          "p": 19,
          "q": 48,
          "value": 0.3958333333333333,
          "prior": 0.008337180354590298,
          "likelihood": 1.5518235905766627e-12,
          "posterior": 8.505546019098866e-16,
          "z_score": -8.093792596409338
        },
        {
          "rational": "8/19",
          "p": 8,
          "q": 19,
          "value": 0.42105263157894735,
          "prior": 0.027362552861460398,
          "likelihood": 1.4347010862114302e-13,
          "posterior": 2.580825809374002e-16,
          "z_score": 8.38281559072516
        },
        {
          "rational": "17/43",
          "p": 17,
          "q": 43,
          "value": 0.3953488372093023,
          "prior": 0.009571320641142777,
          "likelihood": 1.13874780910346e-13,
          "posterior": 7.165393944225499e-17,
          "z_score": -8.410330064109596
        },
        {
          "rational": "15/38",
          "p": 15,
          "q": 38,
          "value": 0.39473684210526316,
          "prior": 0.011187321329846026,
          "likelihood": 3.641534748658651e-15,
          "posterior": 2.6782506768926064e-18,
          "z_score": -8.81016686541517
        },
        {
          "rational": "19/45",
          "p": 19,
          "q": 45,
          "value": 0.4222222222222222,
          "prior": 0.009039741428976587,
          "likelihood": 1.770355264253036e-16,
          "posterior": 1.0521001618065644e-19,
          "z_score": 9.146948144331413
        },
        {
          "rational": "13/33",
          "p": 13,
          "q": 33,
          "value": 0.3939393939393939,
          "prior": 0.013383588085534144,
          "likelihood": 3.2276778180352525e-17,
          "posterior": 2.839902249447513e-20,
          "z_score": -9.331166333783074
        },
        {
          "rational": "11/26",
          "p": 11,
          "q": 26,
          "value": 0.4230769230769231,
          "prior": 0.018174989032245507,
          "likelihood": 9.164434295872408e-19,
          "posterior": 1.0950160173372722e-21,
          "z_score": 9.705352702735969
        },
        {
          "rational": "11/28",
          "p": 11,
          "q": 28,
          "value": 0.39285714285714285,
          "prior": 0.016518625561653393,
          "likelihood": 3.4272196885563495e-20,
          "posterior": 3.7218297704830035e-23,
          "z_score": -10.038237040853776
        },
        {
          "rational": "14/33",
          "p": 14,
          "q": 33,
          "value": 0.42424242424242425,
          "prior": 0.013383588085534144,
          "likelihood": 4.2330760572669873e-22,
          "posterior": 3.724511210487747e-25,
          "z_score": 10.466813464196742
        },
        {
          "rational": "17/40",
          "p": 17,
          "q": 40,
          "value": 0.425,
          "prior": 0.010484829318031567,
          "likelihood": 2.1065837845795305e-24,
          "posterior": 1.4520472691766815e-27,
          "z_score": 10.96176295914622
        },
        {
          "rational": "9/23",
          "p": 9,
          "q": 23,
          "value": 0.391304347826087,
          "prior": 0.021307089376958084,
          "likelihood": 7.73966418990865e-25,
          "posterior": 1.0841438185916637e-27,
          "z_score": -11.052729794476948
        },
        {
          "rational": "20/47",
          "p": 20,
          "q": 47,
          "value": 0.425531914893617,
          "prior": 0.008559918550076194,
          "likelihood": 4.3949075235689275e-26,
          "posterior": 2.4732044882940703e-29,
          "z_score": 11.309280689642684
        },
        {
          "rational": "16/41",
          "p": 16,
          "q": 41,
          "value": 0.3902439024390244,
          "prior": 0.010163152577325599,
          "likelihood": 2.8763174462035818e-28,
          "posterior": 1.9217899308632136e-31,
          "z_score": -11.745554114024493
        },
        {
          "rational": "7/18",
          "p": 7,
          "q": 18,
          "value": 0.3888888888888889,
          "prior": 0.02938584267955792,
          "likelihood": 5.927060466236244e-33,
          "posterior": 1.1450334119814499e-35,
          "z_score": -12.630829633446359
        },
        {
          "rational": "3/7",
          "p": 3,
          "q": 7,
          "value": 0.42857142857142855,
          "prior": 0.10699622539218759,
          "likelihood": 1.0794153640550887e-36,
          "posterior": 7.592725599963525e-39,
          "z_score": 13.295096292479545
        },
        {
          "rational": "19/49",
          "p": 19,
          "q": 49,
          "value": 0.3877551020408163,
          "prior": 0.008124857123602705,
          "likelihood": 3.89366251487855e-37,
          "posterior": 2.0797670399023162e-40,
          "z_score": -13.371570374187112
        },
        {
          "rational": "12/31",
          "p": 12,
          "q": 31,
          "value": 0.3870967741935484,
          "prior": 0.014496262795070576,
          "likelihood": 1.1284117518371596e-39,
          "posterior": 1.0753858221739699e-42,
          "z_score": -13.80167790106883
        },
        {
          "rational": "17/44",
          "p": 17,
          "q": 44,
          "value": 0.38636363636363635,
          "prior": 0.009298569973575145,
          "likelihood": 1.3540220944188079e-42,
          "posterior": 8.277183191041521e-46,
          "z_score": -14.280661283278018
        },
        {
          "rational": "5/13",
          "p": 5,
          "q": 13,
          "value": 0.38461538461538464,
          "prior": 0.04539636044998842,
          "likelihood": 5.813687849008904e-50,
          "posterior": 1.7350556062587018e-52,
          "z_score": -15.42285242546914
        },
        {
          "rational": "19/44",
          "p": 19,
          "q": 44,
          "value": 0.4318181818181818,
          "prior": 0.009298569973575145,
          "likelihood": 6.430941991810771e-50,
          "posterior": 3.9312567480686018e-53,
          "z_score": 15.416308413691686
        },
        {
          "rational": "16/37",
          "p": 16,
          "q": 37,
          "value": 0.43243243243243246,
          "prior": 0.011571727549435393,
          "likelihood": 1.2202323332298156e-52,
          "posterior": 9.282851028175643e-56,
          "z_score": 15.817618815002099
        },
        {
          "rational": "13/30",
          "p": 13,
          "q": 30,
          "value": 0.43333333333333335,
          "prior": 0.01511796325420188,
          "likelihood": 9.287584852396151e-57,
          "posterior": 9.230744548192575e-60,
          "z_score": 16.40620740359068
        },
        {
          "rational": "18/47",
          "p": 18,
          "q": 47,
          "value": 0.3829787234042553,
          "prior": 0.008559918550076194,
          "likelihood": 2.2596172653116404e-57,
          "posterior": 1.2715843353758055e-60,
          "z_score": -16.492137750073628
        },
        {
          "rational": "13/34",
          "p": 13,
          "q": 34,
          "value": 0.38235294117647056,
          "prior": 0.012884043188957292,
          "likelihood": 2.4513916419155778e-60,
          "posterior": 2.0763737294358167e-63,
          "z_score": -16.900982138893003
        },
        {
          "rational": "10/23",
          "p": 10,
          "q": 23,
          "value": 0.43478260869565216,
          "prior": 0.021307089376958084,
          "likelihood": 1.0634701726070765e-63,
          "posterior": 1.4896700755981764e-66,
          "z_score": 17.353067306972306
        },
        {
          "rational": "8/21",
          "p": 8,
          "q": 21,
          "value": 0.38095238095238093,
          "prior": 0.023993242758789796,
          "likelihood": 3.099243818139887e-67,
          "posterior": 4.8886094646886434e-70,
          "z_score": -17.81601481863156
        },
        {
          "rational": "17/39",
          "p": 17,
          "q": 39,
          "value": 0.4358974358974359,
          "prior": 0.010825653993634846,
          "likelihood": 2.644881419678752e-69,
          "posterior": 1.8823526960377091e-72,
          "z_score": 18.08142107880435
        },
        {
          "rational": "19/50",
          "p": 19,
          "q": 50,
          "value": 0.38,
          "prior": 0.00792225758040565,
          "likelihood": 3.915656636282243e-72,
          "posterior": 2.0393614837775472e-75,
          "z_score": -18.438237040853767
        },
        {
          "rational": "11/29",
          "p": 11,
          "q": 29,
          "value": 0.3793103448275862,
          "prior": 0.015790045401325965,
          "likelihood": 8.723419175659722e-76,
          "posterior": 9.055465344101759e-79,
          "z_score": -18.88881175349746
        },
        {
          "rational": "7/16",
          "p": 7,
          "q": 16,
          "value": 0.4375,
          "prior": 0.03435689846767841,
          "likelihood": 9.174025805343616e-78,
          "posterior": 2.0721183722322515e-80,
          "z_score": 19.128429625812895
        },
        {
          "rational": "14/37",
          "p": 14,
          "q": 37,
          "value": 0.3783783783783784,
          "prior": 0.011571727549435393,
          "likelihood": 7.333530522103204e-81,
          "posterior": 5.578943410479347e-84,
          "z_score": -19.497696500313214
        }
      ]
    },
    {
      "key": "lambda_inf_skel",
      "target": {
        "asymptote": 0.29163822550400864,
        "ci95_half": 0.0027718585822512666,
        "label": "Skeleton (tau=0.10) Laplacian asymptote",
        "registered_rational": [
          7,
          24
        ]
      },
      "summary": {
        "n_candidates": 44,
        "top_rational": "7/24",
        "top_posterior": 0.40894982433347543,
        "second_rational": "9/31",
        "second_posterior": 0.19080236532211453,
        "posterior_odds_top_vs_second": 2.143316324423348
      },
      "table": [
        {
          "rational": "7/24",
          "p": 7,
          "q": 24,
          "value": 0.2916666666666667,
          "prior": 0.023294430193102494,
          "likelihood": 282.0377509411511,
          "posterior": 0.40894982433347543,
          "z_score": 0.020110938980332425
        },
        {
          "rational": "9/31",
          "p": 9,
          "q": 31,
          "value": 0.2903225806451613,
          "prior": 0.016749829755795753,
          "likelihood": 183.0048777475942,
          "posterior": 0.19080236532211453,
          "z_score": -0.9303014013241659
        },
        {
          "rational": "12/41",
          "p": 12,
          "q": 41,
          "value": 0.2926829268292683,
          "prior": 0.011743100815630035,
          "likelihood": 214.73247279523852,
          "posterior": 0.1569608009717037,
          "z_score": 0.73871539140566
        },
        {
          "rational": "5/17",
          "p": 5,
          "q": 17,
          "value": 0.29411764705882354,
          "prior": 0.036623928717159866,
          "likelihood": 60.664600726940755,
          "posterior": 0.13829642867617412,
          "z_score": 1.7532157948297071
        },
        {
          "rational": "11/38",
          "p": 11,
          "q": 38,
          "value": 0.2894736842105263,
          "prior": 0.012926485284332979,
          "likelihood": 87.43830008076694,
          "posterior": 0.07035465754368175,
          "z_score": -1.5305618267796448
        },
        {
          "rational": "13/45",
          "p": 13,
          "q": 45,
          "value": 0.28888888888888886,
          "prior": 0.010445045879222039,
          "likelihood": 42.62880505141539,
          "posterior": 0.02771559473828883,
          "z_score": -1.944074564315665
        },
        {
          "rational": "13/44",
          "p": 13,
          "q": 44,
          "value": 0.29545454545454547,
          "prior": 0.010744111515603881,
          "likelihood": 7.397696472729511,
          "posterior": 0.004947407773839705,
          "z_score": 2.6985457162021005
        },
        {
          "rational": "8/27",
          "p": 8,
          "q": 27,
          "value": 0.2962962962962963,
          "prior": 0.020001941117010792,
          "likelihood": 1.2433847263591897,
          "posterior": 0.0015480620498930146,
          "z_score": 3.293753444473583
        },
        {
          "rational": "2/7",
          "p": 2,
          "q": 7,
          "value": 0.2857142857142857,
          "prior": 0.1236296958165877,
          "likelihood": 0.04367311853872726,
          "posterior": 0.0003360838910585575,
          "z_score": -4.188857996653903
        },
        {
          "rational": "11/37",
          "p": 11,
          "q": 37,
          "value": 0.2972972972972973,
          "prior": 0.013370650710016379,
          "likelihood": 0.09404045331234484,
          "posterior": 7.826686692843895e-05,
          "z_score": 4.001568040255936
        },
        {
          "rational": "14/47",
          "p": 14,
          "q": 47,
          "value": 0.2978723404255319,
          "prior": 0.009890630465530011,
          "likelihood": 0.017012548533538625,
          "posterior": 1.0473794406685964e-05,
          "z_score": 4.4081849357053375
        },
        {
          "rational": "3/10",
          "p": 3,
          "q": 10,
          "value": 0.3,
          "prior": 0.07504769275280598,
          "likelihood": 7.227806005099665e-06,
          "posterior": 3.376404916941603e-08,
          "z_score": 5.9126674488682065
        },
        {
          "rational": "13/46",
          "p": 13,
          "q": 46,
          "value": 0.2826086956521739,
          "prior": 0.010160903938967318,
          "likelihood": 3.963932032627124e-07,
          "posterior": 2.507086026980441e-10,
          "z_score": -6.384841789158712
        },
        {
          "rational": "11/39",
          "p": 11,
          "q": 39,
          "value": 0.28205128205128205,
          "prior": 0.012508593694244712,
          "likelihood": 2.9610759769364402e-08,
          "posterior": 2.3055191208467168e-11,
          "z_score": -6.7789927262749465
        },
        {
          "rational": "9/32",
          "p": 9,
          "q": 32,
          "value": 0.28125,
          "prior": 0.016083594176014553,
          "likelihood": 5.415616936044118e-10,
          "posterior": 5.421778058136598e-13,
          "z_score": -7.345584698379549
        },
        {
          "rational": "13/43",
          "p": 13,
          "q": 43,
          "value": 0.3023255813953488,
          "prior": 0.011059263587011623,
          "likelihood": 1.1198559919198316e-10,
          "posterior": 7.709018339049418e-14,
          "z_score": 7.557101823720638
        },
        {
          "rational": "10/33",
          "p": 10,
          "q": 33,
          "value": 0.30303030303030304,
          "prior": 0.015464180328644623,
          "likelihood": 2.289667659436446e-12,
          "posterior": 2.203992168013754e-15,
          "z_score": 8.055415270645637
        },
        {
          "rational": "7/25",
          "p": 7,
          "q": 25,
          "value": 0.28,
          "prior": 0.02209345310506468,
          "likelihood": 5.549879100797286e-13,
          "posterior": 7.632341840005241e-16,
          "z_score": -8.229468174862715
        },
        {
          "rational": "12/43",
          "p": 12,
          "q": 43,
          "value": 0.27906976744186046,
          "prior": 0.011059263587011623,
          "likelihood": 1.9926891046583726e-15,
          "posterior": 1.371754668696283e-18,
          "z_score": -8.88724192480371
        },
        {
          "rational": "7/23",
          "p": 7,
          "q": 23,
          "value": 0.30434782608695654,
          "prior": 0.024619457076684056,
          "likelihood": 8.167132751651397e-16,
          "posterior": 1.2515804702350543e-18,
          "z_score": 8.987044758374957
        },
        {
          "rational": "5/18",
          "p": 5,
          "q": 18,
          "value": 0.2777777777777778,
          "prior": 0.03395412107736942,
          "likelihood": 3.909295307486431e-19,
          "posterior": 8.262313370332086e-22,
          "z_score": -9.800816577499498
        },
        {
          "rational": "11/36",
          "p": 11,
          "q": 36,
          "value": 0.3055555555555556,
          "prior": 0.01384354892885566,
          "likelihood": 2.633571688849166e-19,
          "posterior": 2.2693593769076764e-22,
          "z_score": 9.841038455460161
        },
        {
          "rational": "15/49",
          "p": 15,
          "q": 49,
          "value": 0.30612244897959184,
          "prior": 0.009387935051562862,
          "likelihood": 4.703691781049697e-21,
          "posterior": 2.7486511488231796e-24,
          "z_score": 10.241892639806265
        },
        {
          "rational": "13/47",
          "p": 13,
          "q": 47,
          "value": 0.2765957446808511,
          "prior": 0.009890630465530011,
          "likelihood": 7.634236743719296e-23,
          "posterior": 4.7000263333886283e-26,
          "z_score": -10.636640195923313
        },
        {
          "rational": "8/29",
          "p": 8,
          "q": 29,
          "value": 0.27586206896551724,
          "prior": 0.018244741837767427,
          "likelihood": 2.678057447287043e-25,
          "posterior": 3.041363313293852e-28,
          "z_score": -11.15542726942776
        },
        {
          "rational": "4/13",
          "p": 4,
          "q": 13,
          "value": 0.3076923076923077,
          "prior": 0.05245360958333423,
          "likelihood": 2.9331204202538706e-26,
          "posterior": 9.576701797890698e-29,
          "z_score": 11.351950381072438
        },
        {
          "rational": "11/40",
          "p": 11,
          "q": 40,
          "value": 0.275,
          "prior": 0.01211478493307418,
          "likelihood": 2.4768529405727222e-28,
          "posterior": 1.8677838765494069e-31,
          "z_score": -11.765002080795455
        },
        {
          "rational": "13/42",
          "p": 13,
          "q": 42,
          "value": 0.30952380952380953,
          "prior": 0.011391786192284216,
          "likelihood": 5.2279659982430644e-33,
          "posterior": 3.707108277957851e-36,
          "z_score": 12.647017745882959
        },
        {
          "rational": "9/29",
          "p": 9,
          "q": 29,
          "value": 0.3103448275862069,
          "prior": 0.018244741837767427,
          "likelihood": 2.860699392754152e-36,
          "posterior": 3.2487825055053566e-39,
          "z_score": 13.227565185280781
        },
        {
          "rational": "3/11",
          "p": 3,
          "q": 11,
          "value": 0.2727272727272727,
          "prior": 0.06583620563106135,
          "likelihood": 4.18646986832197e-37,
          "posterior": 1.7156292988749016e-39,
          "z_score": -13.372062947128548
        },
        {
          "rational": "14/45",
          "p": 14,
          "q": 45,
          "value": 0.3111111111111111,
          "prior": 0.010445045879222039,
          "likelihood": 1.9054978546156057e-39,
          "posterior": 1.238880757964184e-42,
          "z_score": 13.769409462052078
        },
        {
          "rational": "5/16",
          "p": 5,
          "q": 16,
          "value": 0.3125,
          "prior": 0.03969796963576442,
          "likelihood": 1.576431202769587e-45,
          "posterior": 3.895417483759944e-48,
          "z_score": 14.751502213700057
        },
        {
          "rational": "13/48",
          "p": 13,
          "q": 48,
          "value": 0.2708333333333333,
          "prior": 0.009633265729029058,
          "likelihood": 2.851051238467565e-45,
          "posterior": 1.709579314136987e-48,
          "z_score": -14.711280335739431
        },
        {
          "rational": "10/37",
          "p": 10,
          "q": 37,
          "value": 0.2702702702702703,
          "prior": 0.013370650710016379,
          "likelihood": 7.530413104407862e-48,
          "posterior": 6.267322408594705e-51,
          "z_score": -15.109426045866968
        },
        {
          "rational": "7/26",
          "p": 7,
          "q": 26,
          "value": 0.2692307692307692,
          "prior": 0.021000445177296823,
          "likelihood": 8.634181555627216e-53,
          "posterior": 1.1286528155864875e-55,
          "z_score": -15.844464279948639
        },
        {
          "rational": "11/35",
          "p": 11,
          "q": 35,
          "value": 0.3142857142857143,
          "prior": 0.014347948465259825,
          "likelihood": 5.781430525394838e-54,
          "posterior": 5.163400480386555e-57,
          "z_score": 16.014192894390316
        },
        {
          "rational": "11/41",
          "p": 11,
          "q": 41,
          "value": 0.2682926829268293,
          "prior": 0.011743100815630035,
          "likelihood": 1.8889174750105608e-57,
          "posterior": 1.380722701078493e-60,
          "z_score": -16.50779146680279
        },
        {
          "rational": "6/19",
          "p": 6,
          "q": 19,
          "value": 0.3157894736842105,
          "prior": 0.031616293702213624,
          "likelihood": 1.3221202033950337e-61,
          "posterior": 2.6019119195842515e-64,
          "z_score": 17.077511362340005
        },
        {
          "rational": "4/15",
          "p": 4,
          "q": 15,
          "value": 0.26666666666666666,
          "prior": 0.043270393535805696,
          "likelihood": 5.574327049199241e-66,
          "posterior": 1.5013916010447e-68,
          "z_score": -17.65755859068337
        },
        {
          "rational": "13/41",
          "p": 13,
          "q": 41,
          "value": 0.3170731707317073,
          "prior": 0.011743100815630035,
          "likelihood": 1.622421514253554e-68,
          "posterior": 1.1859248723587046e-71,
          "z_score": 17.98522224961415
        },
        {
          "rational": "13/49",
          "p": 13,
          "q": 49,
          "value": 0.2653061224489796,
          "prior": 0.009387935051562862,
          "likelihood": 1.4711466325812397e-73,
          "posterior": 8.596798153363215e-77,
          "z_score": -18.61960863311403
        },
        {
          "rational": "7/22",
          "p": 7,
          "q": 22,
          "value": 0.3181818181818182,
          "prior": 0.02608788501957983,
          "likelihood": 8.984915078219396e-75,
          "posterior": 1.4590277092903979e-77,
          "z_score": 18.76915437953271
        },
        {
          "rational": "9/34",
          "p": 9,
          "q": 34,
          "value": 0.2647058823529412,
          "prior": 0.014886976942411576,
          "likelihood": 4.970489938010331e-77,
          "posterior": 4.605920167445575e-80,
          "z_score": -19.04404247536287
        },
        {
          "rational": "15/47",
          "p": 15,
          "q": 47,
          "value": 0.3191489361702128,
          "prior": 0.009890630465530011,
          "likelihood": 1.8950595353680153e-80,
          "posterior": 1.1666955084798176e-83,
          "z_score": 19.453010067334027
        }
      ]
    },
    {
      "key": "lift",
      "target": {
        "asymptote": 1.3983012186166521,
        "ci95_half": 0.05,
        "label": "Weight-lift Symanzik asymptote",
        "registered_rational": [
          9,
          7
        ]
      },
      "summary": {
        "n_candidates": 75,
        "top_rational": "49/50",
        "top_posterior": 0.23832356516389758,
        "second_rational": "48/49",
        "second_posterior": 0.18799110983087863,
        "posterior_odds_top_vs_second": 1.2677384870928166
      },
      "table": [
        {
          "rational": "49/50",
          "p": 49,
          "q": 50,
          "value": 0.98,
          "prior": 0.006346653250627131,
          "likelihood": 6.437773967511511e-58,
          "posterior": 0.23832356516389758,
          "z_score": -16.397407769772762
        },
        {
          "rational": "48/49",
          "p": 48,
          "q": 49,
          "value": 0.9795918367346939,
          "prior": 0.006508959138356337,
          "likelihood": 4.951528411039304e-58,
          "posterior": 0.18799110983087863,
          "z_score": -16.413407769772764
        },
        {
          "rational": "47/48",
          "p": 47,
          "q": 48,
          "value": 0.9791666666666666,
          "prior": 0.006679054835252633,
          "likelihood": 3.7659517335255246e-58,
          "posterior": 0.1467155851106903,
          "z_score": -16.43007443643943
        },
        {
          "rational": "46/47",
          "p": 46,
          "q": 47,
          "value": 0.9787234042553191,
          "prior": 0.0068574941346659455,
          "likelihood": 2.8302429161247294e-58,
          "posterior": 0.11320761688379656,
          "z_score": -16.447450322964254
        },
        {
          "rational": "45/46",
          "p": 45,
          "q": 46,
          "value": 0.9782608695652174,
          "prior": 0.00704488347908756,
          "likelihood": 2.1000969923571926e-58,
          "posterior": 0.08629778695110082,
          "z_score": -16.46558168281624
        },
        {
          "rational": "44/45",
          "p": 44,
          "q": 45,
          "value": 0.9777777777777777,
          "prior": 0.00724188828029817,
          "likelihood": 1.537245594688185e-58,
          "posterior": 0.06493540734230013,
          "z_score": -16.484518880883876
        },
        {
          "rational": "43/44",
          "p": 43,
          "q": 44,
          "value": 0.9772727272727273,
          "prior": 0.007449240162922441,
          "likelihood": 1.1089749146865226e-58,
          "posterior": 0.04818592383960723,
          "z_score": -16.504316860681854
        },
        {
          "rational": "42/43",
          "p": 42,
          "q": 43,
          "value": 0.9767441860465116,
          "prior": 0.0076677452914618496,
          "likelihood": 7.876287325985508e-59,
          "posterior": 0.03522700492278876,
          "z_score": -16.52503567674951
        },
        {
          "rational": "41/42",
          "p": 41,
          "q": 42,
          "value": 0.9761904761904762,
          "prior": 0.007898293973191254,
          "likelihood": 5.501045326978567e-59,
          "posterior": 0.02534340762360337,
          "z_score": -16.546741103106097
        },
        {
          "rational": "40/41",
          "p": 40,
          "q": 41,
          "value": 0.975609756097561,
          "prior": 0.008141871769107547,
          "likelihood": 3.7735086588651442e-59,
          "posterior": 0.017920746659342658,
          "z_score": -16.569505330748374
        },
        {
          "rational": "39/40",
          "p": 39,
          "q": 40,
          "value": 0.975,
          "prior": 0.008399572394381605,
          "likelihood": 2.538740249569636e-59,
          "posterior": 0.012438326061520491,
          "z_score": -16.593407769772764
        },
        {
          "rational": "38/39",
          "p": 38,
          "q": 39,
          "value": 0.9743589743589743,
          "prior": 0.008672612751042252,
          "likelihood": 1.6726174348322055e-59,
          "posterior": 0.008461221523908588,
          "z_score": -16.61853597490097
        },
        {
          "rational": "37/38",
          "p": 37,
          "q": 38,
          "value": 0.9736842105263158,
          "prior": 0.008962350512244005,
          "likelihood": 1.077310107727633e-59,
          "posterior": 0.005631824993504972,
          "z_score": -16.644986717141183
        },
        {
          "rational": "36/37",
          "p": 36,
          "q": 37,
          "value": 0.972972972972973,
          "prior": 0.0092703047738111,
          "likelihood": 6.770622086695038e-60,
          "posterior": 0.0036610788063288807,
          "z_score": -16.67286722923222
        },
        {
          "rational": "35/36",
          "p": 35,
          "q": 36,
          "value": 0.9722222222222222,
          "prior": 0.00959818041058534,
          "likelihood": 4.143276733341501e-60,
          "posterior": 0.0023196333354316566,
          "z_score": -16.702296658661652
        },
        {
          "rational": "34/35",
          "p": 34,
          "q": 35,
          "value": 0.9714285714285714,
          "prior": 0.009947896930121127,
          "likelihood": 2.4629898508607958e-60,
          "posterior": 0.0014291584798432763,
          "z_score": -16.733407769772764
        },
        {
          "rational": "33/34",
          "p": 33,
          "q": 34,
          "value": 0.9705882352941176,
          "prior": 0.010321622814772098,
          "likelihood": 1.418521737785352e-60,
          "posterior": 0.0008540247782478921,
          "z_score": -16.76634894624335
        },
        {
          "rational": "32/33",
          "p": 32,
          "q": 33,
          "value": 0.9696969696969697,
          "prior": 0.01072181659912155,
          "likelihood": 7.891718275677204e-61,
          "posterior": 0.0004935446387222844,
          "z_score": -16.80128655765155
        },
        {
          "rational": "31/32",
          "p": 31,
          "q": 32,
          "value": 0.96875,
          "prior": 0.011151276261988708,
          "likelihood": 4.226781275621362e-61,
          "posterior": 0.0002749291829244906,
          "z_score": -16.838407769772765
        },
        {
          "rational": "30/31",
          "p": 30,
          "q": 31,
          "value": 0.967741935483871,
          "prior": 0.011613198946955842,
          "likelihood": 2.171181130624111e-61,
          "posterior": 0.0001470734951308559,
          "z_score": -16.87792389880502
        },
        {
          "rational": "29/30",
          "p": 29,
          "q": 30,
          "value": 0.9666666666666667,
          "prior": 0.012111253598652741,
          "likelihood": 1.0649942700402594e-61,
          "posterior": 7.523550847268997e-05,
          "z_score": -16.920074436439428
        },
        {
          "rational": "28/29",
          "p": 28,
          "q": 29,
          "value": 0.9655172413793104,
          "prior": 0.012649669864526683,
          "likelihood": 4.963760686292842e-62,
          "posterior": 3.662490591261767e-05,
          "z_score": -16.965131907703796
        },
        {
          "rational": "27/28",
          "p": 27,
          "q": 28,
          "value": 0.9642857142857143,
          "prior": 0.013233347635156267,
          "likelihood": 2.1858221087794445e-62,
          "posterior": 1.6872173283600702e-05,
          "z_score": -17.013407769772762
        },
        {
          "rational": "26/27",
          "p": 26,
          "q": 27,
          "value": 0.9629629629629629,
          "prior": 0.01386799298284014,
          "likelihood": 9.03454981023693e-63,
          "posterior": 7.308136008315128e-06,
          "z_score": -17.065259621624616
        },
        {
          "rational": "25/26",
          "p": 25,
          "q": 26,
          "value": 0.9615384615384616,
          "prior": 0.014560288156612429,
          "likelihood": 3.4783746877219925e-63,
          "posterior": 2.9541519053066386e-06,
          "z_score": -17.12110007746507
        },
        {
          "rational": "24/25",
          "p": 24,
          "q": 25,
          "value": 0.96,
          "prior": 0.015318105919588553,
          "likelihood": 1.2364107138688928e-63,
          "posterior": 1.104725348516293e-06,
          "z_score": -17.181407769772765
        },
        {
          "rational": "23/24",
          "p": 23,
          "q": 24,
          "value": 0.9583333333333334,
          "prior": 0.01615078219495743,
          "likelihood": 4.015431551485516e-64,
          "posterior": 3.782790406048581e-07,
          "z_score": -17.246741103106096
        },
        {
          "rational": "47/49",
          "p": 47,
          "q": 49,
          "value": 0.9591836734693877,
          "prior": 0.006508959138356337,
          "likelihood": 7.131207971001836e-64,
          "posterior": 2.7074543244356676e-07,
          "z_score": -17.213407769772765
        },
        {
          "rational": "22/23",
          "p": 22,
          "q": 23,
          "value": 0.9565217391304348,
          "prior": 0.0170694662074784,
          "likelihood": 1.1768657095689703e-64,
          "posterior": 1.1717456245182115e-07,
          "z_score": -17.31775559585972
        },
        {
          "rational": "45/47",
          "p": 45,
          "q": 47,
          "value": 0.9574468085106383,
          "prior": 0.0068574941346659455,
          "likelihood": 2.203806628662085e-64,
          "posterior": 8.815063013925185e-08,
          "z_score": -17.28149287615574
        },
        {
          "rational": "21/22",
          "p": 21,
          "q": 22,
          "value": 0.9545454545454546,
          "prior": 0.018087574814475857,
          "likelihood": 3.067387753487071e-65,
          "posterior": 3.236201174345292e-08,
          "z_score": -17.395225951590945
        },
        {
          "rational": "43/45",
          "p": 43,
          "q": 45,
          "value": 0.9555555555555556,
          "prior": 0.00724188828029817,
          "likelihood": 6.103259963581043e-65,
          "posterior": 2.578102505029302e-08,
          "z_score": -17.355629991994984
        },
        {
          "rational": "20/21",
          "p": 20,
          "q": 21,
          "value": 0.9523809523809523,
          "prior": 0.019221388676479007,
          "likelihood": 6.985616151380067e-66,
          "posterior": 7.832059356721043e-09,
          "z_score": -17.48007443643943
        },
        {
          "rational": "41/43",
          "p": 41,
          "q": 43,
          "value": 0.9534883720930233,
          "prior": 0.0076677452914618496,
          "likelihood": 1.490558366210513e-65,
          "posterior": 6.6665809322327815e-09,
          "z_score": -17.43666358372625
        },
        {
          "rational": "19/20",
          "p": 19,
          "q": 20,
          "value": 0.95,
          "prior": 0.020490844166259875,
          "likelihood": 1.360733686762332e-66,
          "posterior": 1.6263704628261335e-09,
          "z_score": -17.573407769772764
        },
        {
          "rational": "39/41",
          "p": 39,
          "q": 41,
          "value": 0.9512195121951219,
          "prior": 0.008141871769107547,
          "likelihood": 3.1486569347540914e-66,
          "posterior": 1.4953267196657308e-09,
          "z_score": -17.525602891723985
        },
        {
          "rational": "37/39",
          "p": 37,
          "q": 39,
          "value": 0.9487179487179487,
          "prior": 0.008672612751042252,
          "likelihood": 5.6190908422141696e-67,
          "posterior": 2.8425132602847557e-10,
          "z_score": -17.623664180029174
        },
        {
          "rational": "18/19",
          "p": 18,
          "q": 19,
          "value": 0.9473684210526315,
          "prior": 0.021920599437862794,
          "likelihood": 2.2088071050562046e-67,
          "posterior": 2.824208189936824e-10,
          "z_score": -17.676565664509607
        },
        {
          "rational": "35/37",
          "p": 35,
          "q": 37,
          "value": 0.9459459459459459,
          "prior": 0.0092703047738111,
          "likelihood": 8.230276740494845e-68,
          "posterior": 4.450357937427797e-11,
          "z_score": -17.732326688691682
        },
        {
          "rational": "17/18",
          "p": 17,
          "q": 18,
          "value": 0.9444444444444444,
          "prior": 0.023541490802560367,
          "likelihood": 2.8932572497852673e-68,
          "posterior": 3.9728988050526536e-11,
          "z_score": -17.79118554755054
        },
        {
          "rational": "33/35",
          "p": 33,
          "q": 35,
          "value": 0.9428571428571428,
          "prior": 0.009947896930121127,
          "likelihood": 9.545073268769523e-69,
          "posterior": 5.5385621658245045e-12,
          "z_score": -17.853407769772765
        },
        {
          "rational": "16/17",
          "p": 16,
          "q": 17,
          "value": 0.9411764705882353,
          "prior": 0.02539255482667445,
          "likelihood": 2.9377100379184933e-69,
          "posterior": 4.3511275790602206e-12,
          "z_score": -17.91929012271394
        },
        {
          "rational": "31/33",
          "p": 31,
          "q": 33,
          "value": 0.9393939393939394,
          "prior": 0.01072181659912155,
          "likelihood": 8.378423822198873e-70,
          "posterior": 5.239829925422015e-13,
          "z_score": -17.98916534553034
        },
        {
          "rational": "47/50",
          "p": 47,
          "q": 50,
          "value": 0.94,
          "prior": 0.006346653250627131,
          "likelihood": 1.2842455985101986e-69,
          "posterior": 4.75422080873868e-13,
          "z_score": -17.965407769772764
        },
        {
          "rational": "15/16",
          "p": 15,
          "q": 16,
          "value": 0.9375,
          "prior": 0.027523886862839467,
          "likelihood": 2.1975532769549926e-70,
          "posterior": 3.5280576100064796e-13,
          "z_score": -18.063407769772763
        },
        {
          "rational": "46/49",
          "p": 46,
          "q": 49,
          "value": 0.9387755102040817,
          "prior": 0.006508959138356337,
          "likelihood": 5.4154987589106877e-70,
          "posterior": 2.0560633757156988e-13,
          "z_score": -18.013407769772762
        },
        {
          "rational": "29/31",
          "p": 29,
          "q": 31,
          "value": 0.9354838709677419,
          "prior": 0.011613198946955842,
          "likelihood": 5.255182509339559e-71,
          "posterior": 3.559804607259733e-14,
          "z_score": -18.14244002783728
        },
        {
          "rational": "44/47",
          "p": 44,
          "q": 47,
          "value": 0.9361702127659575,
          "prior": 0.0068574941346659455,
          "likelihood": 8.558867416144242e-71,
          "posterior": 3.423483468100185e-14,
          "z_score": -18.11553542934723
        },
        {
          "rational": "14/15",
          "p": 14,
          "q": 15,
          "value": 0.9333333333333333,
          "prior": 0.030000763946302588,
          "likelihood": 1.134547844124716e-71,
          "posterior": 1.985370753859242e-14,
          "z_score": -18.226741103106097
        },
        {
          "rational": "43/46",
          "p": 43,
          "q": 46,
          "value": 0.9347826086956522,
          "prior": 0.00704488347908756,
          "likelihood": 3.190286220011853e-71,
          "posterior": 1.3109615485835099e-14,
          "z_score": -18.169929508903195
        },
        {
          "rational": "41/44",
          "p": 41,
          "q": 44,
          "value": 0.9318181818181818,
          "prior": 0.007449240162922441,
          "likelihood": 3.8362583858109936e-72,
          "posterior": 1.666887609085335e-15,
          "z_score": -18.28613504250004
        },
        {
          "rational": "27/29",
          "p": 27,
          "q": 29,
          "value": 0.9310344827586207,
          "prior": 0.012649669864526683,
          "likelihood": 2.1864018699776838e-72,
          "posterior": 1.613227708503991e-15,
          "z_score": -18.316856045634832
        },
        {
          "rational": "13/14",
          "p": 13,
          "q": 14,
          "value": 0.9285714285714286,
          "prior": 0.032909726924919155,
          "likelihood": 3.712320505203084e-73,
          "posterior": 7.126170913488092e-16,
          "z_score": -18.41340776977276
        },
        {
          "rational": "40/43",
          "p": 40,
          "q": 43,
          "value": 0.9302325581395349,
          "prior": 0.0076677452914618496,
          "likelihood": 1.22870970107896e-72,
          "posterior": 5.49545247616662e-16,
          "z_score": -18.348291490702998
        },
        {
          "rational": "38/41",
          "p": 38,
          "q": 41,
          "value": 0.926829268292683,
          "prior": 0.008141871769107547,
          "likelihood": 1.0531905653280595e-73,
          "posterior": 5.001700807261494e-17,
          "z_score": -18.48170045269959
        },
        {
          "rational": "25/27",
          "p": 25,
          "q": 27,
          "value": 0.9259259259259259,
          "prior": 0.01386799298284014,
          "likelihood": 5.470261571481708e-74,
          "posterior": 4.424948271373753e-17,
          "z_score": -18.517111473476465
        },
        {
          "rational": "12/13",
          "p": 12,
          "q": 13,
          "value": 0.9230769230769231,
          "prior": 0.03636778477503219,
          "likelihood": 6.873457972574103e-75,
          "posterior": 1.4580708283544066e-17,
          "z_score": -18.628792385157375
        },
        {
          "rational": "37/40",
          "p": 37,
          "q": 40,
          "value": 0.925,
          "prior": 0.008399572394381605,
          "likelihood": 2.7914611248666665e-74,
          "posterior": 1.36765089161982e-17,
          "z_score": -18.55340776977276
        },
        {
          "rational": "35/38",
          "p": 35,
          "q": 38,
          "value": 0.9210526315789473,
          "prior": 0.008962350512244005,
          "likelihood": 1.5624932438370015e-75,
          "posterior": 8.168203788030023e-19,
          "z_score": -18.708144611878026
        },
        {
          "rational": "23/25",
          "p": 23,
          "q": 25,
          "value": 0.92,
          "prior": 0.015318105919588553,
          "likelihood": 7.214258554755879e-76,
          "posterior": 6.445895531955443e-19,
          "z_score": -18.749407769772763
        },
        {
          "rational": "34/37",
          "p": 34,
          "q": 37,
          "value": 0.918918918918919,
          "prior": 0.0092703047738111,
          "likelihood": 3.256301239767024e-76,
          "posterior": 1.7607799258742592e-19,
          "z_score": -18.79178614815114
        },
        {
          "rational": "11/12",
          "p": 11,
          "q": 12,
          "value": 0.9166666666666666,
          "prior": 0.040536755401292424,
          "likelihood": 6.173000419607299e-77,
          "posterior": 1.4595930348599118e-19,
          "z_score": -18.880074436439433
        },
        {
          "rational": "45/49",
          "p": 45,
          "q": 49,
          "value": 0.9183673469387755,
          "prior": 0.006508959138356337,
          "likelihood": 2.1685295806514205e-76,
          "posterior": 8.233099938573986e-20,
          "z_score": -18.813407769772763
        },
        {
          "rational": "43/47",
          "p": 43,
          "q": 47,
          "value": 0.9148936170212766,
          "prior": 0.0068574941346659455,
          "likelihood": 1.6578764160625253e-77,
          "posterior": 6.631382666166058e-21,
          "z_score": -18.94957798253872
        },
        {
          "rational": "32/35",
          "p": 32,
          "q": 35,
          "value": 0.9142857142857143,
          "prior": 0.009947896930121127,
          "likelihood": 1.0551565822365292e-77,
          "posterior": 6.1225829921254265e-21,
          "z_score": -18.973407769772763
        },
        {
          "rational": "21/23",
          "p": 21,
          "q": 23,
          "value": 0.9130434782608695,
          "prior": 0.0170694662074784,
          "likelihood": 4.1835751060290366e-78,
          "posterior": 4.165373997623091e-21,
          "z_score": -19.022103421946678
        },
        {
          "rational": "31/34",
          "p": 31,
          "q": 34,
          "value": 0.9117647058823529,
          "prior": 0.010321622814772098,
          "likelihood": 1.610222071881716e-78,
          "posterior": 9.694384733332383e-22,
          "z_score": -19.07223129918453
        },
        {
          "rational": "10/11",
          "p": 10,
          "q": 11,
          "value": 0.9090909090909091,
          "prior": 0.04564637163799559,
          "likelihood": 2.1693980066186788e-79,
          "posterior": 5.776063910451489e-22,
          "z_score": -19.17704413340913
        },
        {
          "rational": "41/45",
          "p": 41,
          "q": 45,
          "value": 0.9111111111111111,
          "prior": 0.00724188828029817,
          "likelihood": 9.874749684696854e-79,
          "posterior": 4.1712325954598374e-22,
          "z_score": -19.09785221421721
        },
        {
          "rational": "39/43",
          "p": 39,
          "q": 43,
          "value": 0.9069767441860465,
          "prior": 0.0076677452914618496,
          "likelihood": 4.4118674177034216e-80,
          "posterior": 1.973225059088147e-23,
          "z_score": -19.25991939767974
        },
        {
          "rational": "29/32",
          "p": 29,
          "q": 32,
          "value": 0.90625,
          "prior": 0.011151276261988708,
          "likelihood": 2.5477446239310183e-80,
          "posterior": 1.6571696098815716e-23,
          "z_score": -19.288407769772764
        },
        {
          "rational": "19/21",
          "p": 19,
          "q": 21,
          "value": 0.9047619047619048,
          "prior": 0.019221388676479007,
          "likelihood": 8.25595774641841e-81,
          "posterior": 9.256327532934306e-24,
          "z_score": -19.346741103106098
        },
        {
          "rational": "28/31",
          "p": 28,
          "q": 31,
          "value": 0.9032258064516129,
          "prior": 0.011613198946955842,
          "likelihood": 2.570645690474937e-81,
          "posterior": 1.741327985530821e-24,
          "z_score": -19.406956156869537
        },
        {
          "rational": "37/41",
          "p": 37,
          "q": 41,
          "value": 0.9024390243902439,
          "prior": 0.008141871769107547,
          "likelihood": 1.4121804606415637e-81,
          "posterior": 6.706577501280274e-25,
          "z_score": -19.437798013675202
        },
        {
          "rational": "9/10",
          "p": 9,
          "q": 10,
          "value": 0.9,
          "prior": 0.05203299371725145,
          "likelihood": 2.191763101241171e-82,
          "posterior": 6.652102252049748e-25,
          "z_score": -19.53340776977276
        }
      ]
    }
  ]
}